{"id":"1oatkUcXoTb4O1XBztk5Bg","name":"bass and smooth","owner":{"id":"1128723762","display_name":"Peter Pron"},"tracks":[{"added_at":"2015-02-26T14:48:20Z","added_by":{"id":"1128723762","display_name":null},"track":{"id":"1SasjPcy0U1cgyTH2gpypL","uri":"spotify:track:1SasjPcy0U1cgyTH2gpypL","name":"Cat on Tin Roof","artists":[{"id":"5isqImG0rLfAgBJSPMEVXF","type":"artist","name":"Blonde Redhead"}],"album":{"id":"4XvtXHbIkZVLp65p5KBHMP","name":"Barragán"},"preview_url":"https://p.scdn.co/mp3-preview/58c7617c04442037a67314a163a9cd9024073db8?cid=774b29d4f13844c495f206cafdad9c86","track_number":4,"href":"https://api.spotify.com/v1/tracks/1SasjPcy0U1cgyTH2gpypL"}},{"added_at":"2015-02-26T14:48:54Z","added_by":{"id":"1128723762","display_name":null},"track":{"id":"10WBKR8tDk416oDMm6wshS","uri":"spotify:track:10WBKR8tDk416oDMm6wshS","name":"Bobby Reid","artists":[{"id":"1OlzK1kHcdTcduXcdXHYXn","type":"artist","name":"Lucette"}],"album":{"id":"0Gx2t3sH5mQbHDLI5fuEXY","name":"Black Is the Color"},"preview_url":"https://p.scdn.co/mp3-preview/11ed9ff8bac261371bb67e021bb6b42a1826d3f3?cid=774b29d4f13844c495f206cafdad9c86","track_number":1,"href":"https://api.spotify.com/v1/tracks/10WBKR8tDk416oDMm6wshS"}},{"added_at":"2015-02-26T14:49:23Z","added_by":{"id":"1128723762","display_name":null},"track":{"id":"7r3oumwvHjsnh5IPtGrfNB","uri":"spotify:track:7r3oumwvHjsnh5IPtGrfNB","name":"Everything Goes My Way","artists":[{"id":"54QMjE4toDfiCryzYWCpXX","type":"artist","name":"Metronomy"}],"album":{"id":"0KhwLl8JKnXaf6KQKBtMZL","name":"The English Riviera"},"preview_url":null,"track_number":3,"href":"https://api.spotify.com/v1/tracks/7r3oumwvHjsnh5IPtGrfNB"}},{"added_at":"2015-02-26T14:49:42Z","added_by":{"id":"1128723762","display_name":null},"track":{"id":"0gsH5Govmgwxa0rgaF9YbC","uri":"spotify:track:0gsH5Govmgwxa0rgaF9YbC","name":"Never Seen Such Good Things","artists":[{"id":"1YZEoYFXx4AxVv13OiOPvZ","type":"artist","name":"Devendra Banhart"}],"album":{"id":"1Z69PSnbIBojgF9NBJbKca","name":"Mala"},"preview_url":"https://p.scdn.co/mp3-preview/b422e9aa703594116ab4de6c26e73a190dac1bc8?cid=774b29d4f13844c495f206cafdad9c86","track_number":4,"href":"https://api.spotify.com/v1/tracks/0gsH5Govmgwxa0rgaF9YbC"}},{"added_at":"2015-02-26T14:49:48Z","added_by":{"id":"1128723762","display_name":null},"track":{"id":"2CG6feguaKMR3C4zCMjDNR","uri":"spotify:track:2CG6feguaKMR3C4zCMjDNR","name":"Für Hildegard von Bingen","artists":[{"id":"1YZEoYFXx4AxVv13OiOPvZ","type":"artist","name":"Devendra Banhart"}],"album":{"id":"1Z69PSnbIBojgF9NBJbKca","name":"Mala"},"preview_url":"https://p.scdn.co/mp3-preview/e548020d08c89ebaf1acb787d171bdaf320bbce2?cid=774b29d4f13844c495f206cafdad9c86","track_number":3,"href":"https://api.spotify.com/v1/tracks/2CG6feguaKMR3C4zCMjDNR"}},{"added_at":"2015-02-26T14:52:20Z","added_by":{"id":"1128723762","display_name":null},"track":{"id":"2ogCbnrsNL9bB5PL3dNSSQ","uri":"spotify:track:2ogCbnrsNL9bB5PL3dNSSQ","name":"(Sittin' On) The Dock of the Bay","artists":[{"id":"60df5JBRRPcnSpsIMxxwQm","type":"artist","name":"Otis Redding"}],"album":{"id":"0IdJOPJy2DQXaqgyrjhXRc","name":"Pure Southern Soul"},"preview_url":"https://p.scdn.co/mp3-preview/f4a5f20ce3896f0a7a7cb335ff7b544cf0219a9e?cid=774b29d4f13844c495f206cafdad9c86","track_number":60,"href":"https://api.spotify.com/v1/tracks/2ogCbnrsNL9bB5PL3dNSSQ"}},{"added_at":"2015-02-26T14:53:09Z","added_by":{"id":"1128723762","display_name":null},"track":{"id":"4KK8YW1O0yOzZgUJ04UgoW","uri":"spotify:track:4KK8YW1O0yOzZgUJ04UgoW","name":"Brothers & Sisters","artists":[{"id":"09eOcl2G6lhrTanTtoWlVs","type":"artist","name":"Bongmaster inc"}],"album":{"id":"6GDqDZG6ubMRGhoq2BSVXJ","name":"Happy Cones"},"preview_url":"https://p.scdn.co/mp3-preview/14fdb264f5d982b87ead477eab8417eda0299258?cid=774b29d4f13844c495f206cafdad9c86","track_number":1,"href":"https://api.spotify.com/v1/tracks/4KK8YW1O0yOzZgUJ04UgoW"}},{"added_at":"2015-02-26T14:55:12Z","added_by":{"id":"1128723762","display_name":null},"track":{"id":"5d0oZGQTZIeU3vFZ9qykvq","uri":"spotify:track:5d0oZGQTZIeU3vFZ9qykvq","name":"Come Undone","artists":[{"id":"55dlp5I9jyc4UjzlrcKMnq","type":"artist","name":"Isobel Campbell"},{"id":"1fpXM23IoNckJ7NDAm8YJQ","type":"artist","name":"Mark Lanegan"}],"album":{"id":"0cSyiBaPRl6MG4lMuKYL97","name":"Hawk"},"preview_url":"https://p.scdn.co/mp3-preview/7abfdc197652403f6ebb770b36ac176950b1c28a?cid=774b29d4f13844c495f206cafdad9c86","track_number":4,"href":"https://api.spotify.com/v1/tracks/5d0oZGQTZIeU3vFZ9qykvq"}},{"added_at":"2015-02-26T15:02:40Z","added_by":{"id":"1128723762","display_name":null},"track":{"id":"2kFYdRAsmbSecgkdaPKMjH","uri":"spotify:track:2kFYdRAsmbSecgkdaPKMjH","name":"Fantom (The Wandering Ghost)","artists":[{"id":"69H6uUTI29XBzQXV1d3A7D","type":"artist","name":"Jimi Tenor"}],"album":{"id":"7mURlSC12iCw7lLnqjSIVH","name":"Europa"},"preview_url":"https://p.scdn.co/mp3-preview/905bca664f580a0bbbfe98b582e18c6548f55e42?cid=774b29d4f13844c495f206cafdad9c86","track_number":1,"href":"https://api.spotify.com/v1/tracks/2kFYdRAsmbSecgkdaPKMjH"}},{"added_at":"2015-02-26T15:11:57Z","added_by":{"id":"1128723762","display_name":null},"track":{"id":"23XRQfV2iK3dPSe33WbKpr","uri":"spotify:track:23XRQfV2iK3dPSe33WbKpr","name":"Ernie","artists":[{"id":"32lo0J8u6KZJTwBOIBrdYS","type":"artist","name":"Fat Freddy's Drop"}],"album":{"id":"0LnSfxR87BwwU7HnElG8gs","name":"Based on a True Story"},"preview_url":null,"track_number":1,"href":"https://api.spotify.com/v1/tracks/23XRQfV2iK3dPSe33WbKpr"}},{"added_at":"2015-02-26T15:16:05Z","added_by":{"id":"1128723762","display_name":null},"track":{"id":"2tAYoHaFbx6e7QOkOkAhrX","uri":"spotify:track:2tAYoHaFbx6e7QOkOkAhrX","name":"Spill The Wine","artists":[{"id":"3miNucraVWk4hdVsIxn7id","type":"artist","name":"Eric Burdon"},{"id":"3ICyfoySNDZqtBVmaBT84I","type":"artist","name":"War"}],"album":{"id":"4HUntZg0YV0qCvRxmIhq2U","name":"Boogie Nights / Music From The Original Motion Picture"},"preview_url":"https://p.scdn.co/mp3-preview/cc299d2ff8f91aa0ab6058a75e6da96486289a75?cid=774b29d4f13844c495f206cafdad9c86","track_number":5,"href":"https://api.spotify.com/v1/tracks/2tAYoHaFbx6e7QOkOkAhrX"}},{"added_at":"2015-02-26T15:16:41Z","added_by":{"id":"1128723762","display_name":null},"track":{"id":"63G8lZIk7MFSi8lEQS2QJo","uri":"spotify:track:63G8lZIk7MFSi8lEQS2QJo","name":"Who Is He - And What Is He To You?","artists":[{"id":"1ThoqLcyIYvZn7iWbj8fsj","type":"artist","name":"Bill Withers"}],"album":{"id":"1f0FdT3X5hFNDNj39v4Km8","name":"Jackie Brown (Music from the Miramax Motion Picture)"},"preview_url":null,"track_number":5,"href":"https://api.spotify.com/v1/tracks/63G8lZIk7MFSi8lEQS2QJo"}},{"added_at":"2015-02-26T15:16:41Z","added_by":{"id":"1128723762","display_name":null},"track":{"id":"1qfDfZAvrkSAFrAR2FTQDv","uri":"spotify:track:1qfDfZAvrkSAFrAR2FTQDv","name":"Grandma's Hands","artists":[{"id":"1ThoqLcyIYvZn7iWbj8fsj","type":"artist","name":"Bill Withers"}],"album":{"id":"6N8uPmDqbgXD3ztkCCfxoo","name":"Just As I Am"},"preview_url":"https://p.scdn.co/mp3-preview/e93b8b4a7d89ee8e3bd4d6c8517699d5312e7263?cid=774b29d4f13844c495f206cafdad9c86","track_number":3,"href":"https://api.spotify.com/v1/tracks/1qfDfZAvrkSAFrAR2FTQDv"}},{"added_at":"2015-02-26T15:20:55Z","added_by":{"id":"1128723762","display_name":null},"track":{"id":"5c8B0EUBSmxaaZMunqWqHx","uri":"spotify:track:5c8B0EUBSmxaaZMunqWqHx","name":"Not Afraid","artists":[{"id":"5Julda6z6GzFQyKQZLee4F","type":"artist","name":"Mister Modo"},{"id":"3UnSlb3cSKqGqjWyQ7Jvo6","type":"artist","name":"Ugly Mac Beer"}],"album":{"id":"2Ce7n9m4peTZ4oOL6FdnRy","name":"Modonut"},"preview_url":null,"track_number":1,"href":"https://api.spotify.com/v1/tracks/5c8B0EUBSmxaaZMunqWqHx"}},{"added_at":"2015-02-26T15:22:07Z","added_by":{"id":"1128723762","display_name":null},"track":{"id":"5SFDglrlsCldfJPmjL6PCB","uri":"spotify:track:5SFDglrlsCldfJPmjL6PCB","name":"Stand Still","artists":[{"id":"1lc8mnyGrCLtPhCoWjRxjM","type":"artist","name":"Flight Facilities"}],"album":{"id":"2zPeXPtISNIeQIa5QO3HUm","name":"Stand Still (Remixes)"},"preview_url":null,"track_number":1,"href":"https://api.spotify.com/v1/tracks/5SFDglrlsCldfJPmjL6PCB"}},{"added_at":"2015-02-26T15:23:13Z","added_by":{"id":"1128723762","display_name":null},"track":{"id":"311vyS49AokwvMcw7CIfIB","uri":"spotify:track:311vyS49AokwvMcw7CIfIB","name":"Our Way To Fall","artists":[{"id":"5hAhrnb0Ch4ODwWu4tsbpi","type":"artist","name":"Yo La Tengo"}],"album":{"id":"3Dd8XjacY0PngUPEyKUHH5","name":"And Then Nothing Turned Itself Inside-Out"},"preview_url":null,"track_number":2,"href":"https://api.spotify.com/v1/tracks/311vyS49AokwvMcw7CIfIB"}},{"added_at":"2015-02-26T15:28:22Z","added_by":{"id":"1128723762","display_name":null},"track":{"id":"5IyoulMVgZsyNVjWzPHxcZ","uri":"spotify:track:5IyoulMVgZsyNVjWzPHxcZ","name":"Here To Fall (rjd2 Remix)","artists":[{"id":"5hAhrnb0Ch4ODwWu4tsbpi","type":"artist","name":"Yo La Tengo"}],"album":{"id":"2jN9rxykYI9RPKxYZ165Na","name":"Here To Fall Remixes"},"preview_url":"https://p.scdn.co/mp3-preview/107059fdf16d1084506b44baf9c50ce7df4ff832?cid=774b29d4f13844c495f206cafdad9c86","track_number":3,"href":"https://api.spotify.com/v1/tracks/5IyoulMVgZsyNVjWzPHxcZ"}},{"added_at":"2015-02-26T15:29:17Z","added_by":{"id":"1128723762","display_name":null},"track":{"id":"7ElMeCWsfj7IkUGcsWxb5K","uri":"spotify:track:7ElMeCWsfj7IkUGcsWxb5K","name":"There Is An End","artists":[{"id":"7sPZakwiHQUWkG1teFE8zv","type":"artist","name":"The Greenhornes"}],"album":{"id":"4NrdlpNTAeRwF5SrarP2vk","name":"Dual Mono"},"preview_url":"https://p.scdn.co/mp3-preview/d7e5cfe60851e463404f7f697ce2d18cd23fdb59?cid=774b29d4f13844c495f206cafdad9c86","track_number":8,"href":"https://api.spotify.com/v1/tracks/7ElMeCWsfj7IkUGcsWxb5K"}},{"added_at":"2015-02-26T15:30:29Z","added_by":{"id":"1128723762","display_name":null},"track":{"id":"4mPXQqTQh27p8tYVT1SejW","uri":"spotify:track:4mPXQqTQh27p8tYVT1SejW","name":"Somebody Like You","artists":[{"id":"3dGzchO8ZLLvTt5CA3BRlN","type":"artist","name":"AM & Shawn Lee"}],"album":{"id":"7F2wctsLEob7CLG5A4Amh6","name":"Celestial Electric"},"preview_url":"https://p.scdn.co/mp3-preview/b900ad8c5a2f082681c26a6d255b2880f56073dc?cid=774b29d4f13844c495f206cafdad9c86","track_number":7,"href":"https://api.spotify.com/v1/tracks/4mPXQqTQh27p8tYVT1SejW"}},{"added_at":"2015-02-26T15:30:37Z","added_by":{"id":"1128723762","display_name":null},"track":{"id":"1guAaYucjI3fPFsznEr420","uri":"spotify:track:1guAaYucjI3fPFsznEr420","name":"Sors de l'image","artists":[{"id":"3Fx6SNtY9l2QwiVkTvoOZX","type":"artist","name":"Carl Et Les Hommes Boîtes"}],"album":{"id":"2bOuOQuoa0GxUAUoMPb4lo","name":"La paroi de ton ventre"},"preview_url":null,"track_number":6,"href":"https://api.spotify.com/v1/tracks/1guAaYucjI3fPFsznEr420"}},{"added_at":"2015-02-26T15:38:46Z","added_by":{"id":"1128723762","display_name":null},"track":{"id":"6lY62Z0JaYMskxi3raAWJf","uri":"spotify:track:6lY62Z0JaYMskxi3raAWJf","name":"I'm to Blame","artists":[{"id":"1rVQy9vBP9rrWlPze4jIF4","type":"artist","name":"Boardwalk"}],"album":{"id":"0RuYFTQuuBuTeiBkx4HmQu","name":"Boardwalk"},"preview_url":"https://p.scdn.co/mp3-preview/b9b495183cf32a27e12e06c1208818f942c7690b?cid=774b29d4f13844c495f206cafdad9c86","track_number":10,"href":"https://api.spotify.com/v1/tracks/6lY62Z0JaYMskxi3raAWJf"}},{"added_at":"2015-02-26T15:39:08Z","added_by":{"id":"1128723762","display_name":null},"track":{"id":"6p2WHHDyEY7sOffm95faXO","uri":"spotify:track:6p2WHHDyEY7sOffm95faXO","name":"I Heard","artists":[{"id":"5mZC7ndY6oGMxJentRwsuV","type":"artist","name":"Young Fathers"}],"album":{"id":"6rytySC0CxMcD6tg9sazu7","name":"Tape Two"},"preview_url":null,"track_number":1,"href":"https://api.spotify.com/v1/tracks/6p2WHHDyEY7sOffm95faXO"}},{"added_at":"2015-02-26T15:39:32Z","added_by":{"id":"1128723762","display_name":null},"track":{"id":"2H7pdPrM7iuI2e2eUfm0GF","uri":"spotify:track:2H7pdPrM7iuI2e2eUfm0GF","name":"Revolutionary Pilot","artists":[{"id":"6HIihQSWCTPM4WCrpYuc31","type":"artist","name":"Statik Sound System"}],"album":{"id":"2uAOyQjqYLlstUXCGDShuw","name":"DJ-Kicks"},"preview_url":null,"track_number":5,"href":"https://api.spotify.com/v1/tracks/2H7pdPrM7iuI2e2eUfm0GF"}},{"added_at":"2015-02-26T15:40:56Z","added_by":{"id":"1128723762","display_name":null},"track":{"id":"3nN7uDTvd4B2qZuX8CCLIy","uri":"spotify:track:3nN7uDTvd4B2qZuX8CCLIy","name":"Sadnecessary","artists":[{"id":"1hzfo8twXdOegF3xireCYs","type":"artist","name":"Milky Chance"}],"album":{"id":"27chRNopg2v5jii9ps8lio","name":"Sadnecessary"},"preview_url":null,"track_number":7,"href":"https://api.spotify.com/v1/tracks/3nN7uDTvd4B2qZuX8CCLIy"}},{"added_at":"2015-02-26T15:41:01Z","added_by":{"id":"1128723762","display_name":null},"track":{"id":"2BRiUhKwHdKYbHvsmlfqoP","uri":"spotify:track:2BRiUhKwHdKYbHvsmlfqoP","name":"Fairytale","artists":[{"id":"1hzfo8twXdOegF3xireCYs","type":"artist","name":"Milky Chance"}],"album":{"id":"27chRNopg2v5jii9ps8lio","name":"Sadnecessary"},"preview_url":null,"track_number":10,"href":"https://api.spotify.com/v1/tracks/2BRiUhKwHdKYbHvsmlfqoP"}},{"added_at":"2015-02-26T15:41:09Z","added_by":{"id":"1128723762","display_name":null},"track":{"id":"5Xzqo7xSIo1IRrDqsjWfzL","uri":"spotify:track:5Xzqo7xSIo1IRrDqsjWfzL","name":"Say Goodbye","artists":[{"id":"2Kx7MNY7cI1ENniW7vT30N","type":"artist","name":"Norah Jones"}],"album":{"id":"3wNsg8Gyd8kNdD3NVU8p4Y","name":"Little Broken Hearts (Deluxe)"},"preview_url":null,"track_number":2,"href":"https://api.spotify.com/v1/tracks/5Xzqo7xSIo1IRrDqsjWfzL"}},{"added_at":"2015-02-26T15:42:22Z","added_by":{"id":"1128723762","display_name":null},"track":{"id":"1vVooSURdrlFf8dNdqxOJL","uri":"spotify:track:1vVooSURdrlFf8dNdqxOJL","name":"Lovin U","artists":[{"id":"5WQxQAu4xmUwCzxPw3GiB4","type":"artist","name":"Stwo"}],"album":{"id":"1BPMDfCzCQu8wo4Xwe0T5T","name":"Majestic Casual - Chapter I"},"preview_url":null,"track_number":19,"href":"https://api.spotify.com/v1/tracks/1vVooSURdrlFf8dNdqxOJL"}},{"added_at":"2015-02-26T15:45:01Z","added_by":{"id":"1128723762","display_name":null},"track":{"id":"4xWZLAJROTARQNxXvRgnfq","uri":"spotify:track:4xWZLAJROTARQNxXvRgnfq","name":"Sutphin Boulevard","artists":[{"id":"6LEeAFiJF8OuPx747e1wxR","type":"artist","name":"Blood Orange"}],"album":{"id":"4eEIQzWiKSjBoMOEleXqGX","name":"Coastal Grooves"},"preview_url":null,"track_number":2,"href":"https://api.spotify.com/v1/tracks/4xWZLAJROTARQNxXvRgnfq"}},{"added_at":"2015-02-26T15:45:21Z","added_by":{"id":"1128723762","display_name":null},"track":{"id":"1YoO8Y3Jhi2bgguxlJ6kRj","uri":"spotify:track:1YoO8Y3Jhi2bgguxlJ6kRj","name":"Peanut Dreams","artists":[{"id":"21Z32HrM98tvP45zCAsTuH","type":"artist","name":"Grand National"}],"album":{"id":"72mIhTeHOWayHE9CGsaVzO","name":"Sunday Best's Spring Cleaning"},"preview_url":"https://p.scdn.co/mp3-preview/15f6fdccdc1c21003b3ab5d50744d7f4ec61ea81?cid=774b29d4f13844c495f206cafdad9c86","track_number":6,"href":"https://api.spotify.com/v1/tracks/1YoO8Y3Jhi2bgguxlJ6kRj"}},{"added_at":"2015-02-26T15:45:48Z","added_by":{"id":"1128723762","display_name":null},"track":{"id":"1GVafg6PWpBt5rWTMruzwG","uri":"spotify:track:1GVafg6PWpBt5rWTMruzwG","name":"Sunny","artists":[{"id":"2uNpV18izVIP7DNusoWbT5","type":"artist","name":"Bobby Hebb"}],"album":{"id":"4XIbmP53zK67wpaADb3ErR","name":"Golden Moments"},"preview_url":null,"track_number":17,"href":"https://api.spotify.com/v1/tracks/1GVafg6PWpBt5rWTMruzwG"}},{"added_at":"2015-02-26T15:46:03Z","added_by":{"id":"1128723762","display_name":null},"track":{"id":"2iN3sND7JNguttGbuyr8pe","uri":"spotify:track:2iN3sND7JNguttGbuyr8pe","name":"Duet","artists":[{"id":"6pdYN3jOHWteVALy9sKGEf","type":"artist","name":"Gonjasufi"}],"album":{"id":"3FfW96Pt3UxQlchDVhkaFi","name":"A Sufi And A Killer"},"preview_url":"https://p.scdn.co/mp3-preview/a7c04a291a8ac3da1911d5df180529cebdc39ffc?cid=774b29d4f13844c495f206cafdad9c86","track_number":10,"href":"https://api.spotify.com/v1/tracks/2iN3sND7JNguttGbuyr8pe"}},{"added_at":"2015-02-26T15:46:17Z","added_by":{"id":"1128723762","display_name":null},"track":{"id":"4c7ra5L7SBRlxoVEweTdf8","uri":"spotify:track:4c7ra5L7SBRlxoVEweTdf8","name":"The Truth","artists":[{"id":"3pkmfqaBNsMqnXus05PNfP","type":"artist","name":"Handsome Boy Modeling School"}],"album":{"id":"67TjfZMYEYhzHPqSYF7LOv","name":"So..Hows Your Girl"},"preview_url":null,"track_number":7,"href":"https://api.spotify.com/v1/tracks/4c7ra5L7SBRlxoVEweTdf8"}},{"added_at":"2015-02-26T15:51:05Z","added_by":{"id":"1128723762","display_name":null},"track":{"id":"59tpgfXjTc3QR7mWJj8Wln","uri":"spotify:track:59tpgfXjTc3QR7mWJj8Wln","name":"jasmine (demo)","artists":[{"id":"53wZLCnhshZKDRs3uopFBc","type":"artist","name":"Jai Paul"}],"album":{"id":"6KSoqRuevAguR3m0R11sAr","name":"jasmine (demo)"},"preview_url":"https://p.scdn.co/mp3-preview/2b3c8449847b3cc774bf73451a2c1bd391f53b2e?cid=774b29d4f13844c495f206cafdad9c86","track_number":1,"href":"https://api.spotify.com/v1/tracks/59tpgfXjTc3QR7mWJj8Wln"}},{"added_at":"2015-02-26T15:53:18Z","added_by":{"id":"1128723762","display_name":null},"track":{"id":"3Cibi7EZuoKWftzIc5NCz5","uri":"spotify:track:3Cibi7EZuoKWftzIc5NCz5","name":"Nightbird","artists":[{"id":"3le5O6so782djcAD0TbiAC","type":"artist","name":"The Fabulous Three"}],"album":{"id":"57eg3xSuJqbjkcLyfjFToQ","name":"Truth & Soul presents The Best of The Fabulous Three"},"preview_url":"https://p.scdn.co/mp3-preview/72a685333b2a39aa0113abdfc4d031059f0e67b5?cid=774b29d4f13844c495f206cafdad9c86","track_number":3,"href":"https://api.spotify.com/v1/tracks/3Cibi7EZuoKWftzIc5NCz5"}},{"added_at":"2015-02-26T15:53:31Z","added_by":{"id":"1128723762","display_name":null},"track":{"id":"0SMddcOzbuLddEPBeekllO","uri":"spotify:track:0SMddcOzbuLddEPBeekllO","name":"Outta Space","artists":[{"id":"69H6uUTI29XBzQXV1d3A7D","type":"artist","name":"Jimi Tenor"}],"album":{"id":"38EjVIza2iioCropPkLuVo","name":"Intervision"},"preview_url":"https://p.scdn.co/mp3-preview/5f8f9da844f2c2ef13b16d9fc154e75f7a4654ff?cid=774b29d4f13844c495f206cafdad9c86","track_number":1,"href":"https://api.spotify.com/v1/tracks/0SMddcOzbuLddEPBeekllO"}},{"added_at":"2015-02-26T16:03:45Z","added_by":{"id":"1128723762","display_name":null},"track":{"id":"2K8jMkavsyLjVjCePiYbEe","uri":"spotify:track:2K8jMkavsyLjVjCePiYbEe","name":"Sweet Dogs","artists":[{"id":"08Dy6nbbKqKbN5J7hRODRh","type":"artist","name":"Trolle Siebenhaar"}],"album":{"id":"6iVBPYi5Aj24B27qG5Y9Mo","name":"Couple Therapy"},"preview_url":"https://p.scdn.co/mp3-preview/ceda53f31cc059a81a03be7e0991383d6752039b?cid=774b29d4f13844c495f206cafdad9c86","track_number":3,"href":"https://api.spotify.com/v1/tracks/2K8jMkavsyLjVjCePiYbEe"}},{"added_at":"2015-02-26T16:04:27Z","added_by":{"id":"1128723762","display_name":null},"track":{"id":"0r5GDT0CqxmHcSJpvcEoHz","uri":"spotify:track:0r5GDT0CqxmHcSJpvcEoHz","name":"Delicado","artists":[{"id":"6sVKyrNdC2TTvhvOTTgewi","type":"artist","name":"Edmundo Ros"}],"album":{"id":"7FDsMgln5Geh6HL5p8u98a","name":"Calypso & Samba Best"},"preview_url":"https://p.scdn.co/mp3-preview/bcd0901bafe15a93d5a11608e19414debcc9ba32?cid=774b29d4f13844c495f206cafdad9c86","track_number":3,"href":"https://api.spotify.com/v1/tracks/0r5GDT0CqxmHcSJpvcEoHz"}},{"added_at":"2015-02-26T16:04:49Z","added_by":{"id":"1128723762","display_name":null},"track":{"id":"50zQMqNT8w1SfeYKoDQCIP","uri":"spotify:track:50zQMqNT8w1SfeYKoDQCIP","name":"Dub Experience II","artists":[{"id":"484sZUYmnRXN84zmk3GY1n","type":"artist","name":"St Germain"}],"album":{"id":"7i7UOdfGr4p3xmQX7lOT8z","name":"Boulevard (The Complete Series)"},"preview_url":"https://p.scdn.co/mp3-preview/b39f25153d07df5b18decbf63344372469d3c4ec?cid=774b29d4f13844c495f206cafdad9c86","track_number":7,"href":"https://api.spotify.com/v1/tracks/50zQMqNT8w1SfeYKoDQCIP"}},{"added_at":"2015-02-26T16:13:01Z","added_by":{"id":"1128723762","display_name":null},"track":{"id":"40h5ghzluWMW6nkhEFrGWf","uri":"spotify:track:40h5ghzluWMW6nkhEFrGWf","name":"Call It A Day","artists":[{"id":"4wo1267SJuUfHgasdlfNfc","type":"artist","name":"The Raconteurs"}],"album":{"id":"0ftyDJlAoBMmICs2MHvVZR","name":"Broken Boy Soldiers"},"preview_url":null,"track_number":9,"href":"https://api.spotify.com/v1/tracks/40h5ghzluWMW6nkhEFrGWf"}},{"added_at":"2015-02-26T16:17:20Z","added_by":{"id":"1128723762","display_name":null},"track":{"id":"1ejdUvmTVqwr5OLL4jeWK1","uri":"spotify:track:1ejdUvmTVqwr5OLL4jeWK1","name":"Ten Cent Pistol","artists":[{"id":"7mnBLXK823vNxN3UWB7Gfz","type":"artist","name":"The Black Keys"}],"album":{"id":"6BhS0iZh607Op7sWvSXT4o","name":"Brothers"},"preview_url":null,"track_number":9,"href":"https://api.spotify.com/v1/tracks/1ejdUvmTVqwr5OLL4jeWK1"}},{"added_at":"2015-02-26T16:20:50Z","added_by":{"id":"1128723762","display_name":null},"track":{"id":"5IXwDeUkx1pO1z13NE7doI","uri":"spotify:track:5IXwDeUkx1pO1z13NE7doI","name":"Wander","artists":[{"id":"5INjqkS1o8h1imAzPqGZBb","type":"artist","name":"Tame Impala"}],"album":{"id":"19KL6IwPJMECn2wosxguq7","name":"InnerSpeaker (Collector's Edition)"},"preview_url":null,"track_number":4,"href":"https://api.spotify.com/v1/tracks/5IXwDeUkx1pO1z13NE7doI"}},{"added_at":"2015-02-26T16:22:59Z","added_by":{"id":"1128723762","display_name":null},"track":{"id":"6Nv4yPNmbsE9SOh2AVaDcp","uri":"spotify:track:6Nv4yPNmbsE9SOh2AVaDcp","name":"Feels Like We Only Go Backwards","artists":[{"id":"5INjqkS1o8h1imAzPqGZBb","type":"artist","name":"Tame Impala"}],"album":{"id":"7jSu3vVowa6N2zgUeYom2e","name":"Feels Like We Only Go Backwards"},"preview_url":null,"track_number":1,"href":"https://api.spotify.com/v1/tracks/6Nv4yPNmbsE9SOh2AVaDcp"}},{"added_at":"2015-02-26T16:23:31Z","added_by":{"id":"1128723762","display_name":null},"track":{"id":"4is6sxpAf2VbfnCaf998Hr","uri":"spotify:track:4is6sxpAf2VbfnCaf998Hr","name":"Mi vida","artists":[{"id":"6wH6iStAh4KIaWfuhf0NYM","type":"artist","name":"Manu Chao"}],"album":{"id":"20Rg7vDflSF5gYQ1HNDOge","name":"Proxima Estacion: Esperanza"},"preview_url":null,"track_number":8,"href":"https://api.spotify.com/v1/tracks/4is6sxpAf2VbfnCaf998Hr"}},{"added_at":"2015-02-26T16:27:23Z","added_by":{"id":"1128723762","display_name":null},"track":{"id":"4LZxCSEA0ntfrP4ULZsmlB","uri":"spotify:track:4LZxCSEA0ntfrP4ULZsmlB","name":"Pusherman","artists":[{"id":"2AV6XDIs32ofIJhkkDevjm","type":"artist","name":"Curtis Mayfield"}],"album":{"id":"0oY0JQR52E8uSBBBUr8x8b","name":"Beautiful Brother - The Essential"},"preview_url":null,"track_number":3,"href":"https://api.spotify.com/v1/tracks/4LZxCSEA0ntfrP4ULZsmlB"}},{"added_at":"2015-02-26T16:27:57Z","added_by":{"id":"1128723762","display_name":null},"track":{"id":"3RVupqMb1zXl8FNG9TlWBZ","uri":"spotify:track:3RVupqMb1zXl8FNG9TlWBZ","name":"Mykonos","artists":[{"id":"4EVpmkEwrLYEg6jIsiPMIb","type":"artist","name":"Fleet Foxes"}],"album":{"id":"1THgsJygpeEj3yfXuRm7Bb","name":"Sun Giant"},"preview_url":null,"track_number":4,"href":"https://api.spotify.com/v1/tracks/3RVupqMb1zXl8FNG9TlWBZ"}},{"added_at":"2015-02-26T16:28:22Z","added_by":{"id":"1128723762","display_name":null},"track":{"id":"0BRcttewXPSGMKxx87qLfL","uri":"spotify:track:0BRcttewXPSGMKxx87qLfL","name":"Emnete","artists":[{"id":"7HGFXtBhRq3g1Ma3nH4Rgv","type":"artist","name":"Mulatu Astatke"}],"album":{"id":"2tk008RE6FPitI7T72iSIy","name":"Juke Joint II"},"preview_url":null,"track_number":9,"href":"https://api.spotify.com/v1/tracks/0BRcttewXPSGMKxx87qLfL"}},{"added_at":"2015-02-26T16:29:41Z","added_by":{"id":"1128723762","display_name":null},"track":{"id":"199gqmbbEOKoXoLdXKdMnt","uri":"spotify:track:199gqmbbEOKoXoLdXKdMnt","name":"Tear That Falls","artists":[{"id":"5tdgsoMr7dIrcVUVauzuvM","type":"artist","name":"The Aggrolites"}],"album":{"id":"4CfMz3DkCnFRpB6VWI2I1O","name":"IV"},"preview_url":null,"track_number":13,"href":"https://api.spotify.com/v1/tracks/199gqmbbEOKoXoLdXKdMnt"}},{"added_at":"2015-02-26T16:33:07Z","added_by":{"id":"1128723762","display_name":null},"track":{"id":"313y5mBXX9iX3A3PaqlaTx","uri":"spotify:track:313y5mBXX9iX3A3PaqlaTx","name":"Auntie's Lock/Infinitum","artists":[{"id":"29XOeO6KIWxGthejQqn793","type":"artist","name":"Flying Lotus"},{"id":"67OokTsDsLUvJI6oIxCigq","type":"artist","name":"Laura Darlington"}],"album":{"id":"7pdhnkO0t8HiRv4dmggt2I","name":"Los Angeles"},"preview_url":"https://p.scdn.co/mp3-preview/bb6a5098adfc5b8fa9dde164c361b47b05b87c02?cid=774b29d4f13844c495f206cafdad9c86","track_number":17,"href":"https://api.spotify.com/v1/tracks/313y5mBXX9iX3A3PaqlaTx"}},{"added_at":"2015-02-26T16:42:08Z","added_by":{"id":"1128723762","display_name":null},"track":{"id":"2kJTwDF9AhyUpeafmbeDMs","uri":"spotify:track:2kJTwDF9AhyUpeafmbeDMs","name":"Test","artists":[{"id":"6Tyzp9KzpiZ04DABQoedps","type":"artist","name":"Little Dragon"}],"album":{"id":"34AtsFexhxnKPVJFtLIN1I","name":"Little Dragon"},"preview_url":"https://p.scdn.co/mp3-preview/773aefa31107029c1b22d64f8ab0268f1ad6551c?cid=774b29d4f13844c495f206cafdad9c86","track_number":10,"href":"https://api.spotify.com/v1/tracks/2kJTwDF9AhyUpeafmbeDMs"}},{"added_at":"2015-02-26T16:43:05Z","added_by":{"id":"1128723762","display_name":null},"track":{"id":"3Nbgpc2ooFHtkCT9ZLRFXg","uri":"spotify:track:3Nbgpc2ooFHtkCT9ZLRFXg","name":"Animal - Mark Ronson Remix","artists":[{"id":"4l1cKWYW591xnwEGxpUg3J","type":"artist","name":"Miike Snow"},{"id":"3hv9jJF3adDNsBSIQDqcjp","type":"artist","name":"Mark Ronson"}],"album":{"id":"1AMTbO4k2kPRAn6udg9qJz","name":"Miike Snow"},"preview_url":"https://p.scdn.co/mp3-preview/9fe98b55a49e8db042c3cf6a24b71c35285c2925?cid=774b29d4f13844c495f206cafdad9c86","track_number":12,"href":"https://api.spotify.com/v1/tracks/3Nbgpc2ooFHtkCT9ZLRFXg"}},{"added_at":"2015-02-26T16:43:50Z","added_by":{"id":"1128723762","display_name":null},"track":{"id":"4ABWPP59ItFKykdaDF09K5","uri":"spotify:track:4ABWPP59ItFKykdaDF09K5","name":"Make Love","artists":[{"id":"4tZwfgrHOc3mvqYlEYSvVi","type":"artist","name":"Daft Punk"}],"album":{"id":"2T7DdrOvsqOqU9bGTkjBYu","name":"Human After All"},"preview_url":"https://p.scdn.co/mp3-preview/bde6c79c759bd1ec25f5fc2b9d84c1e73d81d2e8?cid=774b29d4f13844c495f206cafdad9c86","track_number":5,"href":"https://api.spotify.com/v1/tracks/4ABWPP59ItFKykdaDF09K5"}},{"added_at":"2015-02-26T16:44:29Z","added_by":{"id":"1128723762","display_name":null},"track":{"id":"714TY3YgigKX2jIX7SREwF","uri":"spotify:track:714TY3YgigKX2jIX7SREwF","name":"Little Man","artists":[{"id":"6Tyzp9KzpiZ04DABQoedps","type":"artist","name":"Little Dragon"}],"album":{"id":"1BQVdofe7ROnSoaiC9418p","name":"Ritual Union"},"preview_url":"https://p.scdn.co/mp3-preview/dd3d76da4f117a4a79f7ad227c50c4c3a8ae0fb4?cid=774b29d4f13844c495f206cafdad9c86","track_number":2,"href":"https://api.spotify.com/v1/tracks/714TY3YgigKX2jIX7SREwF"}},{"added_at":"2015-02-26T16:44:56Z","added_by":{"id":"1128723762","display_name":null},"track":{"id":"3W0lCMgZjxLhO3i4xxSgED","uri":"spotify:track:3W0lCMgZjxLhO3i4xxSgED","name":"Live Your Life","artists":[{"id":"3kHVioJpVxlazAAKQ64pC1","type":"artist","name":"Yuna"}],"album":{"id":"48flyXcU4K9nDuTYV52sSd","name":"Live Your Life"},"preview_url":null,"track_number":1,"href":"https://api.spotify.com/v1/tracks/3W0lCMgZjxLhO3i4xxSgED"}},{"added_at":"2015-02-26T16:45:35Z","added_by":{"id":"1128723762","display_name":null},"track":{"id":"7p8ZlNvYfd7ZosTEdFbv1I","uri":"spotify:track:7p8ZlNvYfd7ZosTEdFbv1I","name":"Green Eyed Love","artists":[{"id":"4d53BMrRlQkrQMz5d59f2O","type":"artist","name":"Mayer Hawthorne"}],"album":{"id":"7JfH5D3XhtWJiAQHweJ4cX","name":"A Strange Arrangement"},"preview_url":"https://p.scdn.co/mp3-preview/3748f6e7952616511a8f18443166089beb325312?cid=774b29d4f13844c495f206cafdad9c86","track_number":12,"href":"https://api.spotify.com/v1/tracks/7p8ZlNvYfd7ZosTEdFbv1I"}},{"added_at":"2015-02-26T16:54:38Z","added_by":{"id":"1128723762","display_name":null},"track":{"id":"1FE45v3BxmGjFiDwuSpeDJ","uri":"spotify:track:1FE45v3BxmGjFiDwuSpeDJ","name":"This Land Is Your Land","artists":[{"id":"6LufpoVlIYKQCu9Gjpk8B7","type":"artist","name":"Sharon Jones & The Dap-Kings"}],"album":{"id":"1ARyfw246YulT9j3B2qfXl","name":"Naturally"},"preview_url":"https://p.scdn.co/mp3-preview/5cc55b973ac461058493d597d7150abe7bbcc350?cid=774b29d4f13844c495f206cafdad9c86","track_number":7,"href":"https://api.spotify.com/v1/tracks/1FE45v3BxmGjFiDwuSpeDJ"}},{"added_at":"2015-02-26T17:00:47Z","added_by":{"id":"1128723762","display_name":null},"track":{"id":"4lqK60MHxN4EDZTDYXkRul","uri":"spotify:track:4lqK60MHxN4EDZTDYXkRul","name":"Golden Cage","artists":[{"id":"1qcU8NabUQ5efQf8UGW6CV","type":"artist","name":"The Whitest Boy Alive"}],"album":{"id":"63BiMHrNanPPTIcDArNX4E","name":"Dreams"},"preview_url":null,"track_number":2,"href":"https://api.spotify.com/v1/tracks/4lqK60MHxN4EDZTDYXkRul"}},{"added_at":"2015-02-27T08:11:57Z","added_by":{"id":"1128723762","display_name":null},"track":{"id":"4JVSkSJAKbSlwkSepkXcK6","uri":"spotify:track:4JVSkSJAKbSlwkSepkXcK6","name":"Something Good","artists":[{"id":"3XHO7cRUPCLOr6jwp8vsx5","type":"artist","name":"alt-J"}],"album":{"id":"7HOzvP7Ta2lLueojdlJtdZ","name":"An Awesome Wave"},"preview_url":"https://p.scdn.co/mp3-preview/7a91a14b49542bc271ea76c493c91be3579f7121?cid=774b29d4f13844c495f206cafdad9c86","track_number":6,"href":"https://api.spotify.com/v1/tracks/4JVSkSJAKbSlwkSepkXcK6"}},{"added_at":"2015-02-26T19:40:12Z","added_by":{"id":"1128723762","display_name":null},"track":{"id":"2TUdxbIF3rpY887d8m0ZGV","uri":"spotify:track:2TUdxbIF3rpY887d8m0ZGV","name":"Baby","artists":[{"id":"5H0YoDsPDi9fObFmJtTjfN","type":"artist","name":"Ariel Pink"}],"album":{"id":"2TIa83EYZBDWfmEj6VVoWu","name":"Mature Themes"},"preview_url":"https://p.scdn.co/mp3-preview/08dc36572cec683a016ee94cf0cc1b9a560d18e6?cid=774b29d4f13844c495f206cafdad9c86","track_number":13,"href":"https://api.spotify.com/v1/tracks/2TUdxbIF3rpY887d8m0ZGV"}},{"added_at":"2015-05-04T08:42:38Z","added_by":{"id":"1128723762","display_name":null},"track":{"id":"4xONa2vsxsDJr4xZxc18I8","uri":"spotify:track:4xONa2vsxsDJr4xZxc18I8","name":"Shuggie","artists":[{"id":"55LHFEtIplWhsfyWZUwkf4","type":"artist","name":"Foxygen"}],"album":{"id":"2PvrxQzGjHFSOBKX2KqLBL","name":"We Are The 21st Century Ambassadors Of Peace & Magic"},"preview_url":null,"track_number":6,"href":"https://api.spotify.com/v1/tracks/4xONa2vsxsDJr4xZxc18I8"}}]}
