{"id":"4TS0cRHux8nBxD6WafSy1H","name":"Jeru The Damaja – Wrath Of The Math","owner":{"id":"1128723762","display_name":"Peter Pron"},"tracks":[{"added_at":"2013-12-02T21:33:54Z","added_by":{"id":"1128723762","display_name":null},"track":{"id":"55yMsGkearEqbKhTN9i0mL","uri":"spotify:track:55yMsGkearEqbKhTN9i0mL","name":"Wrath Of The Math","artists":[{"id":"6CsOL9C9iLL0eWKINlDxzQ","type":"artist","name":"Jeru The Damaja"}],"album":{"id":"7jvuTIYaBYqbTcLZZwXlIZ","name":"Wrath Of The Math"},"preview_url":"https://p.scdn.co/mp3-preview/875155527e2158bc6cf16f5c7c3efaa002a93186?cid=774b29d4f13844c495f206cafdad9c86","track_number":1,"href":"https://api.spotify.com/v1/tracks/55yMsGkearEqbKhTN9i0mL"}},{"added_at":"2013-12-02T21:33:54Z","added_by":{"id":"1128723762","display_name":null},"track":{"id":"6NBBkLU0VJwNS6K8AHSjWk","uri":"spotify:track:6NBBkLU0VJwNS6K8AHSjWk","name":"The Frustrated Nigga","artists":[{"id":"6CsOL9C9iLL0eWKINlDxzQ","type":"artist","name":"Jeru The Damaja"}],"album":{"id":"7jvuTIYaBYqbTcLZZwXlIZ","name":"Wrath Of The Math"},"preview_url":"https://p.scdn.co/mp3-preview/27cd2b19ad047788241664584b7fd9c0f843dcef?cid=774b29d4f13844c495f206cafdad9c86","track_number":2,"href":"https://api.spotify.com/v1/tracks/6NBBkLU0VJwNS6K8AHSjWk"}},{"added_at":"2013-12-02T21:33:54Z","added_by":{"id":"1128723762","display_name":null},"track":{"id":"5PP40QWsX9BWFyG3PUhsQ5","uri":"spotify:track:5PP40QWsX9BWFyG3PUhsQ5","name":"Black Cowboy","artists":[{"id":"6CsOL9C9iLL0eWKINlDxzQ","type":"artist","name":"Jeru The Damaja"}],"album":{"id":"7jvuTIYaBYqbTcLZZwXlIZ","name":"Wrath Of The Math"},"preview_url":"https://p.scdn.co/mp3-preview/4a8bb7ed1b5999ddb7eb512ec104862419822008?cid=774b29d4f13844c495f206cafdad9c86","track_number":3,"href":"https://api.spotify.com/v1/tracks/5PP40QWsX9BWFyG3PUhsQ5"}},{"added_at":"2013-12-02T21:33:54Z","added_by":{"id":"1128723762","display_name":null},"track":{"id":"7MstStHOHSYgrRfWtjSqma","uri":"spotify:track:7MstStHOHSYgrRfWtjSqma","name":"Tha Bullshit","artists":[{"id":"6CsOL9C9iLL0eWKINlDxzQ","type":"artist","name":"Jeru The Damaja"}],"album":{"id":"7jvuTIYaBYqbTcLZZwXlIZ","name":"Wrath Of The Math"},"preview_url":"https://p.scdn.co/mp3-preview/0a17ed11028429002331eee86e5678a8a25e5658?cid=774b29d4f13844c495f206cafdad9c86","track_number":4,"href":"https://api.spotify.com/v1/tracks/7MstStHOHSYgrRfWtjSqma"}},{"added_at":"2013-12-02T21:33:54Z","added_by":{"id":"1128723762","display_name":null},"track":{"id":"0cDUxvPe7BYTCllkCxqSWP","uri":"spotify:track:0cDUxvPe7BYTCllkCxqSWP","name":"Whatever","artists":[{"id":"6CsOL9C9iLL0eWKINlDxzQ","type":"artist","name":"Jeru The Damaja"}],"album":{"id":"7jvuTIYaBYqbTcLZZwXlIZ","name":"Wrath Of The Math"},"preview_url":"https://p.scdn.co/mp3-preview/316329ee309f05b1c104698689ca7b987a20550e?cid=774b29d4f13844c495f206cafdad9c86","track_number":5,"href":"https://api.spotify.com/v1/tracks/0cDUxvPe7BYTCllkCxqSWP"}},{"added_at":"2013-12-02T21:33:54Z","added_by":{"id":"1128723762","display_name":null},"track":{"id":"4xdwPChQKkltOsJOcnnrBp","uri":"spotify:track:4xdwPChQKkltOsJOcnnrBp","name":"Physical Stamina","artists":[{"id":"6CsOL9C9iLL0eWKINlDxzQ","type":"artist","name":"Jeru The Damaja"}],"album":{"id":"7jvuTIYaBYqbTcLZZwXlIZ","name":"Wrath Of The Math"},"preview_url":"https://p.scdn.co/mp3-preview/b6b323f356077679fc3a69d318aefec42611d801?cid=774b29d4f13844c495f206cafdad9c86","track_number":6,"href":"https://api.spotify.com/v1/tracks/4xdwPChQKkltOsJOcnnrBp"}},{"added_at":"2013-12-02T21:33:54Z","added_by":{"id":"1128723762","display_name":null},"track":{"id":"4AeZaDPbZaxoRpPHkrTiCv","uri":"spotify:track:4AeZaDPbZaxoRpPHkrTiCv","name":"One Day","artists":[{"id":"6CsOL9C9iLL0eWKINlDxzQ","type":"artist","name":"Jeru The Damaja"}],"album":{"id":"7jvuTIYaBYqbTcLZZwXlIZ","name":"Wrath Of The Math"},"preview_url":"https://p.scdn.co/mp3-preview/77166f5aa42e00534fb4e35dbd2bdabb2d23f16a?cid=774b29d4f13844c495f206cafdad9c86","track_number":7,"href":"https://api.spotify.com/v1/tracks/4AeZaDPbZaxoRpPHkrTiCv"}},{"added_at":"2013-12-02T21:33:54Z","added_by":{"id":"1128723762","display_name":null},"track":{"id":"5pESmLuMWdFbh1xbo7UXCT","uri":"spotify:track:5pESmLuMWdFbh1xbo7UXCT","name":"Revenge Of The Prophet (Part 5)","artists":[{"id":"6CsOL9C9iLL0eWKINlDxzQ","type":"artist","name":"Jeru The Damaja"}],"album":{"id":"7jvuTIYaBYqbTcLZZwXlIZ","name":"Wrath Of The Math"},"preview_url":"https://p.scdn.co/mp3-preview/4ef3423c173778c4034a91a09bbf48208f448fc2?cid=774b29d4f13844c495f206cafdad9c86","track_number":8,"href":"https://api.spotify.com/v1/tracks/5pESmLuMWdFbh1xbo7UXCT"}},{"added_at":"2013-12-02T21:33:54Z","added_by":{"id":"1128723762","display_name":null},"track":{"id":"6K2RMoEVl670iVJXzL1kiD","uri":"spotify:track:6K2RMoEVl670iVJXzL1kiD","name":"Scientifical Madness","artists":[{"id":"6CsOL9C9iLL0eWKINlDxzQ","type":"artist","name":"Jeru The Damaja"}],"album":{"id":"7jvuTIYaBYqbTcLZZwXlIZ","name":"Wrath Of The Math"},"preview_url":"https://p.scdn.co/mp3-preview/a5186ed2dbd9712b9886cf6893d290a06f243fcb?cid=774b29d4f13844c495f206cafdad9c86","track_number":9,"href":"https://api.spotify.com/v1/tracks/6K2RMoEVl670iVJXzL1kiD"}},{"added_at":"2013-12-02T21:33:54Z","added_by":{"id":"1128723762","display_name":null},"track":{"id":"5mVYEZdc93cs8QvnzPCxmF","uri":"spotify:track:5mVYEZdc93cs8QvnzPCxmF","name":"Not Tha Average","artists":[{"id":"6CsOL9C9iLL0eWKINlDxzQ","type":"artist","name":"Jeru The Damaja"}],"album":{"id":"7jvuTIYaBYqbTcLZZwXlIZ","name":"Wrath Of The Math"},"preview_url":"https://p.scdn.co/mp3-preview/c917a9d52657013dc038eb61be2728ac594aff8b?cid=774b29d4f13844c495f206cafdad9c86","track_number":10,"href":"https://api.spotify.com/v1/tracks/5mVYEZdc93cs8QvnzPCxmF"}},{"added_at":"2013-12-02T21:33:54Z","added_by":{"id":"1128723762","display_name":null},"track":{"id":"1h20yRsf5WeuHbohrlfcCt","uri":"spotify:track:1h20yRsf5WeuHbohrlfcCt","name":"Me Or The Papes","artists":[{"id":"6CsOL9C9iLL0eWKINlDxzQ","type":"artist","name":"Jeru The Damaja"}],"album":{"id":"7jvuTIYaBYqbTcLZZwXlIZ","name":"Wrath Of The Math"},"preview_url":"https://p.scdn.co/mp3-preview/91dbd2bb37b54b94d4a3605353af25e2a756355c?cid=774b29d4f13844c495f206cafdad9c86","track_number":11,"href":"https://api.spotify.com/v1/tracks/1h20yRsf5WeuHbohrlfcCt"}},{"added_at":"2013-12-02T21:33:54Z","added_by":{"id":"1128723762","display_name":null},"track":{"id":"5v72Rt1Pa9qdDcQsvjkJHa","uri":"spotify:track:5v72Rt1Pa9qdDcQsvjkJHa","name":"How I'm Living","artists":[{"id":"6CsOL9C9iLL0eWKINlDxzQ","type":"artist","name":"Jeru The Damaja"}],"album":{"id":"7jvuTIYaBYqbTcLZZwXlIZ","name":"Wrath Of The Math"},"preview_url":"https://p.scdn.co/mp3-preview/8bc1c248a0fde28f46272b44d5b4321e75001498?cid=774b29d4f13844c495f206cafdad9c86","track_number":12,"href":"https://api.spotify.com/v1/tracks/5v72Rt1Pa9qdDcQsvjkJHa"}},{"added_at":"2013-12-02T21:33:54Z","added_by":{"id":"1128723762","display_name":null},"track":{"id":"5YzeqKDY8EKSaGr2ySnVwa","uri":"spotify:track:5YzeqKDY8EKSaGr2ySnVwa","name":"Too Perverted","artists":[{"id":"6CsOL9C9iLL0eWKINlDxzQ","type":"artist","name":"Jeru The Damaja"}],"album":{"id":"7jvuTIYaBYqbTcLZZwXlIZ","name":"Wrath Of The Math"},"preview_url":"https://p.scdn.co/mp3-preview/346291e0c185c50e583efaecc11b8c4b3b1dddb2?cid=774b29d4f13844c495f206cafdad9c86","track_number":13,"href":"https://api.spotify.com/v1/tracks/5YzeqKDY8EKSaGr2ySnVwa"}},{"added_at":"2013-12-02T21:33:54Z","added_by":{"id":"1128723762","display_name":null},"track":{"id":"1KFIhbTUmGKUG1wUw5M8Am","uri":"spotify:track:1KFIhbTUmGKUG1wUw5M8Am","name":"Ya Playin' Yaself","artists":[{"id":"6CsOL9C9iLL0eWKINlDxzQ","type":"artist","name":"Jeru The Damaja"}],"album":{"id":"7jvuTIYaBYqbTcLZZwXlIZ","name":"Wrath Of The Math"},"preview_url":"https://p.scdn.co/mp3-preview/34f8828e826b82cd64aa79913b3659cacce62dde?cid=774b29d4f13844c495f206cafdad9c86","track_number":14,"href":"https://api.spotify.com/v1/tracks/1KFIhbTUmGKUG1wUw5M8Am"}},{"added_at":"2013-12-02T21:33:54Z","added_by":{"id":"1128723762","display_name":null},"track":{"id":"20OfJWmQj13pwiTVC6YxXo","uri":"spotify:track:20OfJWmQj13pwiTVC6YxXo","name":"Invasion","artists":[{"id":"6CsOL9C9iLL0eWKINlDxzQ","type":"artist","name":"Jeru The Damaja"}],"album":{"id":"7jvuTIYaBYqbTcLZZwXlIZ","name":"Wrath Of The Math"},"preview_url":"https://p.scdn.co/mp3-preview/63673726f6c3997657c5b48412a1a196dd1bb615?cid=774b29d4f13844c495f206cafdad9c86","track_number":15,"href":"https://api.spotify.com/v1/tracks/20OfJWmQj13pwiTVC6YxXo"}}]}
