{"id":"4ZhMo7mKIBUuiHgIsrhjPD","name":"w02","owner":{"id":"1128723762","display_name":"Peter Pron"},"tracks":[{"added_at":"2016-01-14T16:18:26Z","added_by":{"id":"1128723762","display_name":null},"track":{"id":"4hWyUpWaHjkRGUugxE0uqN","uri":"spotify:track:4hWyUpWaHjkRGUugxE0uqN","name":"Shame","artists":[{"id":"5mZC7ndY6oGMxJentRwsuV","type":"artist","name":"Young Fathers"}],"album":{"id":"4iTrTerKX84YQRGKxmPCsv","name":"Shame"},"preview_url":null,"track_number":1,"href":"https://api.spotify.com/v1/tracks/4hWyUpWaHjkRGUugxE0uqN"}},{"added_at":"2016-01-14T16:18:26Z","added_by":{"id":"1128723762","display_name":null},"track":{"id":"4IY3uqkCnXeLMW41RAOPpO","uri":"spotify:track:4IY3uqkCnXeLMW41RAOPpO","name":"In Conflict","artists":[{"id":"77Rj6PHmQJFb8nbSH62y68","type":"artist","name":"Owen Pallett"}],"album":{"id":"6qkTG87rvoVj6RqzHHymbi","name":"In Conflict"},"preview_url":null,"track_number":2,"href":"https://api.spotify.com/v1/tracks/4IY3uqkCnXeLMW41RAOPpO"}},{"added_at":"2016-01-14T16:18:26Z","added_by":{"id":"1128723762","display_name":null},"track":{"id":"2tKkXTc9RvtEwNDYR2Fb8f","uri":"spotify:track:2tKkXTc9RvtEwNDYR2Fb8f","name":"Making a Fool of You","artists":[{"id":"4DMSJzGjw2SMkKAT5EEE5u","type":"artist","name":"HOMESHAKE"}],"album":{"id":"4tkb9DzZOrtjIRlD97yW0c","name":"In the Shower"},"preview_url":null,"track_number":4,"href":"https://api.spotify.com/v1/tracks/2tKkXTc9RvtEwNDYR2Fb8f"}},{"added_at":"2016-01-14T16:18:26Z","added_by":{"id":"1128723762","display_name":null},"track":{"id":"1EuDKWkbFHtJpjPbGoAbAs","uri":"spotify:track:1EuDKWkbFHtJpjPbGoAbAs","name":"The Narcissist (feat. Inga Copeland)","artists":[{"id":"5CFSYjc0PAiQvndFjafabk","type":"artist","name":"Dean Blunt"}],"album":{"id":"3RSU9wXiPWb7954IOwZX7E","name":"The Narcissist II"},"preview_url":null,"track_number":8,"href":"https://api.spotify.com/v1/tracks/1EuDKWkbFHtJpjPbGoAbAs"}},{"added_at":"2016-01-14T16:18:26Z","added_by":{"id":"1128723762","display_name":null},"track":{"id":"6VNooTY5w9A9wg1YUsEbKB","uri":"spotify:track:6VNooTY5w9A9wg1YUsEbKB","name":"Midas","artists":[{"id":"7zrkALJ9ayRjzysp4QYoEg","type":"artist","name":"Maribou State"},{"id":"5vssQp6TyMHsx4mihKVAsC","type":"artist","name":"Holly Walker"}],"album":{"id":"4nNZ5UJCzhlfJbip0SDLI1","name":"Portraits"},"preview_url":"https://p.scdn.co/mp3-preview/87725b031b87dd1124364858014998057705376d?cid=774b29d4f13844c495f206cafdad9c86","track_number":8,"href":"https://api.spotify.com/v1/tracks/6VNooTY5w9A9wg1YUsEbKB"}},{"added_at":"2016-01-14T16:18:26Z","added_by":{"id":"1128723762","display_name":null},"track":{"id":"07e4Q3cujOUph7MvNWWJ0E","uri":"spotify:track:07e4Q3cujOUph7MvNWWJ0E","name":"Medicine Chest Dub","artists":[{"id":"3U5oimD8ITVHMJQoxypQPN","type":"artist","name":"Nostalgia 77"},{"id":"2KQRgrZISaDwQNpiLUTAnr","type":"artist","name":"Prince Fatty"}],"album":{"id":"0edpkknHmwJf1kwajgkwh3","name":"In The Kingdom Of Dub"},"preview_url":null,"track_number":1,"href":"https://api.spotify.com/v1/tracks/07e4Q3cujOUph7MvNWWJ0E"}},{"added_at":"2016-01-14T16:18:26Z","added_by":{"id":"1128723762","display_name":null},"track":{"id":"4r8mi2ejg5dATIgXW5IiYf","uri":"spotify:track:4r8mi2ejg5dATIgXW5IiYf","name":"Now You Know My Name","artists":[{"id":"5AztyG5JSIPM9UozcKMlBq","type":"artist","name":"The Derevolutions"}],"album":{"id":"77UXk3f1qOysFaTvBoFh8n","name":"The Derevolutions"},"preview_url":"https://p.scdn.co/mp3-preview/265c941ea7237aea739242db31b0e4c3a6444b97?cid=774b29d4f13844c495f206cafdad9c86","track_number":1,"href":"https://api.spotify.com/v1/tracks/4r8mi2ejg5dATIgXW5IiYf"}},{"added_at":"2016-01-14T16:18:26Z","added_by":{"id":"1128723762","display_name":null},"track":{"id":"11qwSJRR2XGOXi9ehSmZ4T","uri":"spotify:track:11qwSJRR2XGOXi9ehSmZ4T","name":"Apply","artists":[{"id":"2M45qKMZX16QUyOiKyluI0","type":"artist","name":"Glasser"}],"album":{"id":"4yIc2xhi7JEBdMcvybuhbw","name":"Ring"},"preview_url":"https://p.scdn.co/mp3-preview/9629faef0a508e62119e28e2131031e6f07aa4a7?cid=774b29d4f13844c495f206cafdad9c86","track_number":1,"href":"https://api.spotify.com/v1/tracks/11qwSJRR2XGOXi9ehSmZ4T"}},{"added_at":"2016-01-14T16:18:26Z","added_by":{"id":"1128723762","display_name":null},"track":{"id":"69zzEUjJNcz5gCFstcF1Sn","uri":"spotify:track:69zzEUjJNcz5gCFstcF1Sn","name":"Open Eye Signal","artists":[{"id":"7yxi31szvlbwvKq9dYOmFI","type":"artist","name":"Jon Hopkins"}],"album":{"id":"3T0f43xzDQQKvQgFTKjPqq","name":"Immunity"},"preview_url":null,"track_number":2,"href":"https://api.spotify.com/v1/tracks/69zzEUjJNcz5gCFstcF1Sn"}},{"added_at":"2016-01-14T16:18:26Z","added_by":{"id":"1128723762","display_name":null},"track":{"id":"5nwmpDEN8CqQoLeypoaenL","uri":"spotify:track:5nwmpDEN8CqQoLeypoaenL","name":"Future People","artists":[{"id":"16GcWuvvybAoaHr0NqT8Eh","type":"artist","name":"Alabama Shakes"}],"album":{"id":"2IVZPDXb7LFbyukqaoWpYR","name":"Sound & Color"},"preview_url":null,"track_number":4,"href":"https://api.spotify.com/v1/tracks/5nwmpDEN8CqQoLeypoaenL"}},{"added_at":"2016-01-14T16:18:26Z","added_by":{"id":"1128723762","display_name":null},"track":{"id":"2BCFf69uK4HL8eOubSSrHm","uri":"spotify:track:2BCFf69uK4HL8eOubSSrHm","name":"The Trip","artists":[{"id":"4zKYrXs8iN4AeHmO8ZxNqp","type":"artist","name":"Still Corners"}],"album":{"id":"66I4VlmRYrzUvO5LRgZfOf","name":"Strange Pleasures"},"preview_url":null,"track_number":1,"href":"https://api.spotify.com/v1/tracks/2BCFf69uK4HL8eOubSSrHm"}},{"added_at":"2016-01-14T16:18:26Z","added_by":{"id":"1128723762","display_name":null},"track":{"id":"5pgbnjKcz6qSWcyMYyHIxB","uri":"spotify:track:5pgbnjKcz6qSWcyMYyHIxB","name":"Workinonit","artists":[{"id":"0IVcLMMbm05VIjnzPkGCyp","type":"artist","name":"J Dilla"}],"album":{"id":"3WBB77ZEYHvQiwNDZg5y15","name":"Donuts"},"preview_url":"https://p.scdn.co/mp3-preview/5add062d6830332a2c600c7684b5c6d4245a96db?cid=774b29d4f13844c495f206cafdad9c86","track_number":2,"href":"https://api.spotify.com/v1/tracks/5pgbnjKcz6qSWcyMYyHIxB"}},{"added_at":"2016-01-14T16:18:26Z","added_by":{"id":"1128723762","display_name":null},"track":{"id":"0xSOvEMLdWkPOpFNQJLbgZ","uri":"spotify:track:0xSOvEMLdWkPOpFNQJLbgZ","name":"EveryLittleThing","artists":[{"id":"4l2MwXYwUDQKHcUXwCZjEz","type":"artist","name":"José James"}],"album":{"id":"3ZVBGsaIxXkD8nupeXF3Q0","name":"While You Were Sleeping"},"preview_url":null,"track_number":10,"href":"https://api.spotify.com/v1/tracks/0xSOvEMLdWkPOpFNQJLbgZ"}},{"added_at":"2016-01-14T16:18:26Z","added_by":{"id":"1128723762","display_name":null},"track":{"id":"6sLZmlIz35Igd2Itci5484","uri":"spotify:track:6sLZmlIz35Igd2Itci5484","name":"Sleeping Ute (Nicolas Jaar Remix)","artists":[{"id":"2Jv5eshHtLycR6R8KQCdc4","type":"artist","name":"Grizzly Bear"},{"id":"5a0etAzO5V26gvlbmHzT9W","type":"artist","name":"Nicolas Jaar"}],"album":{"id":"1MPysIbKYmbuyPOo2cvPAH","name":"Shields: B-Sides"},"preview_url":"https://p.scdn.co/mp3-preview/73596e3dd84815264ad6e7d6a19aec3d25353493?cid=774b29d4f13844c495f206cafdad9c86","track_number":6,"href":"https://api.spotify.com/v1/tracks/6sLZmlIz35Igd2Itci5484"}},{"added_at":"2016-01-14T16:18:26Z","added_by":{"id":"1128723762","display_name":null},"track":{"id":"6tcJLEjYIYxpTd2zq2K0K7","uri":"spotify:track:6tcJLEjYIYxpTd2zq2K0K7","name":"Still Life (Connan Mockasin Remix)","artists":[{"id":"7EFB09NxZrMi9pGlOnuBpd","type":"artist","name":"The Horrors"}],"album":{"id":"7EYEnHzXomb6Njvdmg6Wob","name":"Higher"},"preview_url":"https://p.scdn.co/mp3-preview/e2f82af4c68cab02486bc0f1cd6ac2dbbbe6d8b4?cid=774b29d4f13844c495f206cafdad9c86","track_number":3,"href":"https://api.spotify.com/v1/tracks/6tcJLEjYIYxpTd2zq2K0K7"}},{"added_at":"2016-01-14T16:18:26Z","added_by":{"id":"1128723762","display_name":null},"track":{"id":"3SYQfqBPcusDPOXumIvXZK","uri":"spotify:track:3SYQfqBPcusDPOXumIvXZK","name":"Superego","artists":[{"id":"0uG3hwOGxuGEOAyocfCwfl","type":"artist","name":"Leyya"}],"album":{"id":"1bbFYH3F3aDP3uvXwZVIpt","name":"Spanish Disco"},"preview_url":null,"track_number":9,"href":"https://api.spotify.com/v1/tracks/3SYQfqBPcusDPOXumIvXZK"}},{"added_at":"2016-01-14T16:18:26Z","added_by":{"id":"1128723762","display_name":null},"track":{"id":"1E9xBiFmTfqnR1ffUEjrTm","uri":"spotify:track:1E9xBiFmTfqnR1ffUEjrTm","name":"Jazzin","artists":[{"id":"3MUQZCYEpUvvV1QNtY7cXq","type":"artist","name":"Flap Jack"}],"album":{"id":"7HxO7QUK01t9p7pHPvxvhC","name":"Flap Jack (Deluxe Edition)"},"preview_url":null,"track_number":5,"href":"https://api.spotify.com/v1/tracks/1E9xBiFmTfqnR1ffUEjrTm"}},{"added_at":"2016-01-14T16:18:26Z","added_by":{"id":"1128723762","display_name":null},"track":{"id":"6Ur2L9zwFT2H2oa5Mnafcs","uri":"spotify:track:6Ur2L9zwFT2H2oa5Mnafcs","name":"Rhythm of Devotion","artists":[{"id":"6WW7gF6rdDASW1brWmFUzM","type":"artist","name":"Sisyphus"}],"album":{"id":"7cD7cpvMp636T6umawpsgK","name":"Sisyphus"},"preview_url":"https://p.scdn.co/mp3-preview/3615639fddef35a11251fc6c4e54ffd037629cc7?cid=774b29d4f13844c495f206cafdad9c86","track_number":4,"href":"https://api.spotify.com/v1/tracks/6Ur2L9zwFT2H2oa5Mnafcs"}},{"added_at":"2016-01-14T16:18:26Z","added_by":{"id":"1128723762","display_name":null},"track":{"id":"4sNLBpbPZH0SiKycWFMtEd","uri":"spotify:track:4sNLBpbPZH0SiKycWFMtEd","name":"Just A Memory","artists":[{"id":"2DcAdoxP41GECOfZt2MhQL","type":"artist","name":"Dirty Art Club"}],"album":{"id":"3y5LcxSDeZJ04KJS7mSvm4","name":"Heavy Starch"},"preview_url":null,"track_number":4,"href":"https://api.spotify.com/v1/tracks/4sNLBpbPZH0SiKycWFMtEd"}},{"added_at":"2016-01-14T16:18:26Z","added_by":{"id":"1128723762","display_name":null},"track":{"id":"74CXQDbpYhp5mu8La3VreE","uri":"spotify:track:74CXQDbpYhp5mu8La3VreE","name":"Sketch for A Summer","artists":[{"id":"7fh7bwX9qV60tLxxsp9bTe","type":"artist","name":"The Durutti Column"}],"album":{"id":"6alOwXJTwVyZE8ktbWA6De","name":"The Return Of The Durutti Column"},"preview_url":null,"track_number":1,"href":"https://api.spotify.com/v1/tracks/74CXQDbpYhp5mu8La3VreE"}},{"added_at":"2016-01-14T16:18:26Z","added_by":{"id":"1128723762","display_name":null},"track":{"id":"1lQU3PkJm50NDMFIJ5WEDu","uri":"spotify:track:1lQU3PkJm50NDMFIJ5WEDu","name":"Warm & Easy","artists":[{"id":"0tCMgjr8y7UKNmE3B1Uwbl","type":"artist","name":"The 2 Bears"}],"album":{"id":"0DSCXv8rx9jJgdqZnJ2LH9","name":"Be Strong"},"preview_url":"https://p.scdn.co/mp3-preview/b160f5dbf9ad9fed9dcbcfb9241bbfaaee95f40e?cid=774b29d4f13844c495f206cafdad9c86","track_number":5,"href":"https://api.spotify.com/v1/tracks/1lQU3PkJm50NDMFIJ5WEDu"}},{"added_at":"2016-01-14T16:18:26Z","added_by":{"id":"1128723762","display_name":null},"track":{"id":"1K5RjfNOb6OLnQcAUv6M6b","uri":"spotify:track:1K5RjfNOb6OLnQcAUv6M6b","name":"Confessions (feat. Leland Whitty)","artists":[{"id":"65dGLGjkw3UbddUg2GKQoZ","type":"artist","name":"BADBADNOTGOOD"},{"id":"2QobOeybSvyibNUGIobnlP","type":"artist","name":"Leland Whitty"}],"album":{"id":"6IoZzmLWjNLruCmqvlPOPV","name":"III"},"preview_url":null,"track_number":3,"href":"https://api.spotify.com/v1/tracks/1K5RjfNOb6OLnQcAUv6M6b"}},{"added_at":"2016-01-14T16:18:26Z","added_by":{"id":"1128723762","display_name":null},"track":{"id":"1TjDt5ukh4Q3OwXaVcz784","uri":"spotify:track:1TjDt5ukh4Q3OwXaVcz784","name":"Right On","artists":[{"id":"78xUyw6FkVZrRAtziFdtdu","type":"artist","name":"The Roots"},{"id":"4gn6f5jaOO75s0oF7ozqGG","type":"artist","name":"Joanna Newsom"},{"id":"09e1aib7HBYGg3XBOVhVsN","type":"artist","name":"STS"}],"album":{"id":"4kQoUjU1uRgZDHYjdDl5mz","name":"How I Got Over"},"preview_url":null,"track_number":9,"href":"https://api.spotify.com/v1/tracks/1TjDt5ukh4Q3OwXaVcz784"}},{"added_at":"2016-01-14T16:18:26Z","added_by":{"id":"1128723762","display_name":null},"track":{"id":"3m5i3P2r5qDImP45cACsBW","uri":"spotify:track:3m5i3P2r5qDImP45cACsBW","name":"Kuj Yato","artists":[{"id":"4o6gglPeg2GgT0FYDtzFeF","type":"artist","name":"Clap! Clap!"}],"album":{"id":"4MNSQRDHy6IPaePn1wpqL6","name":"Tayi Bebba"},"preview_url":null,"track_number":17,"href":"https://api.spotify.com/v1/tracks/3m5i3P2r5qDImP45cACsBW"}},{"added_at":"2016-01-14T16:18:26Z","added_by":{"id":"1128723762","display_name":null},"track":{"id":"5VxNxXOYe9zUqFCGTLmBzE","uri":"spotify:track:5VxNxXOYe9zUqFCGTLmBzE","name":"Ultimate Painting","artists":[{"id":"1PPpmEpuN1KrWNOBqrHeMj","type":"artist","name":"Ultimate Painting"}],"album":{"id":"1EApty6jfl0QKRE07Mqun1","name":"Ultimate Painting"},"preview_url":null,"track_number":1,"href":"https://api.spotify.com/v1/tracks/5VxNxXOYe9zUqFCGTLmBzE"}},{"added_at":"2016-01-14T16:18:26Z","added_by":{"id":"1128723762","display_name":null},"track":{"id":"6uNA1IG5XDm609HAnFh1dH","uri":"spotify:track:6uNA1IG5XDm609HAnFh1dH","name":"Other Men's Girls","artists":[{"id":"0EgHhNmWcjusA7F2heSD0O","type":"artist","name":"Baxter Dury"}],"album":{"id":"5hxVaM0tTV8hrqD1HokIUO","name":"It's A Pleasure"},"preview_url":"https://p.scdn.co/mp3-preview/7429e04f785c5c23258c9146ae59bcfffc4a6d6f?cid=774b29d4f13844c495f206cafdad9c86","track_number":3,"href":"https://api.spotify.com/v1/tracks/6uNA1IG5XDm609HAnFh1dH"}},{"added_at":"2016-01-14T16:18:26Z","added_by":{"id":"1128723762","display_name":null},"track":{"id":"0nghE8iUqF4SkTaMqQNxiG","uri":"spotify:track:0nghE8iUqF4SkTaMqQNxiG","name":"Pussy","artists":[{"id":"6HdYUuBeK3g2MA2wGVCDcn","type":"artist","name":"Brazilian Girls"}],"album":{"id":"2GqHFaFJmhDgHGQQQcWqRE","name":"Brazilian Girls"},"preview_url":"https://p.scdn.co/mp3-preview/c187d4c2d40fbab4a83ef70c07514296ae4b3c97?cid=774b29d4f13844c495f206cafdad9c86","track_number":7,"href":"https://api.spotify.com/v1/tracks/0nghE8iUqF4SkTaMqQNxiG"}},{"added_at":"2016-01-14T16:18:26Z","added_by":{"id":"1128723762","display_name":null},"track":{"id":"4H1N9jJNDqNOEeZ04PlyRP","uri":"spotify:track:4H1N9jJNDqNOEeZ04PlyRP","name":"The Sweetest","artists":[{"id":"4tNxq9NGKTKaX8OkZBLgf0","type":"artist","name":"Nightmares On Wax"}],"album":{"id":"76IdrUoD3S7mXFww6H78Cf","name":"In A Space Outta Sound"},"preview_url":"https://p.scdn.co/mp3-preview/28fd84955b5c8442e69140f4e88cd58d26834501?cid=774b29d4f13844c495f206cafdad9c86","track_number":2,"href":"https://api.spotify.com/v1/tracks/4H1N9jJNDqNOEeZ04PlyRP"}},{"added_at":"2016-01-14T16:18:26Z","added_by":{"id":"1128723762","display_name":null},"track":{"id":"1oMwz5PBptPBZEM9dQCIX1","uri":"spotify:track:1oMwz5PBptPBZEM9dQCIX1","name":"Love Letters (Soulwax Remix)","artists":[{"id":"54QMjE4toDfiCryzYWCpXX","type":"artist","name":"Metronomy"}],"album":{"id":"37e6opxQu4vF3agRuX5iPx","name":"Love Letters (Soulwax Remix)"},"preview_url":null,"track_number":1,"href":"https://api.spotify.com/v1/tracks/1oMwz5PBptPBZEM9dQCIX1"}},{"added_at":"2016-01-14T16:18:26Z","added_by":{"id":"1128723762","display_name":null},"track":{"id":"4igKl8YqB7HsDP9ZKJbUEy","uri":"spotify:track:4igKl8YqB7HsDP9ZKJbUEy","name":"San Francisco","artists":[{"id":"55LHFEtIplWhsfyWZUwkf4","type":"artist","name":"Foxygen"}],"album":{"id":"2PvrxQzGjHFSOBKX2KqLBL","name":"We Are The 21st Century Ambassadors Of Peace & Magic"},"preview_url":null,"track_number":4,"href":"https://api.spotify.com/v1/tracks/4igKl8YqB7HsDP9ZKJbUEy"}},{"added_at":"2016-01-14T16:19:04Z","added_by":{"id":"1128723762","display_name":null},"track":{"id":"1fSspAntWGCxAZ5wx6CNq1","uri":"spotify:track:1fSspAntWGCxAZ5wx6CNq1","name":"Life of Eve","artists":[{"id":"49nLjoMp9cuHBsYHBsmets","type":"artist","name":"Babel feat. Låpsley"},{"id":"5efe1RTjjCtJ904lJg1gDK","type":"artist","name":"Babel"},{"id":"27ze6hCgfr3HcDZAHY60pg","type":"artist","name":"Låpsley"}],"album":{"id":"3wMvfDAFnNd90IndhgfYm3","name":"Life of Eve"},"preview_url":null,"track_number":1,"href":"https://api.spotify.com/v1/tracks/1fSspAntWGCxAZ5wx6CNq1"}},{"added_at":"2016-01-14T16:19:04Z","added_by":{"id":"1128723762","display_name":null},"track":{"id":"0xirw16sHgeRNcYirbHCK5","uri":"spotify:track:0xirw16sHgeRNcYirbHCK5","name":"Aile Mut","artists":[{"id":"37cUr70U6qVVqoBwWsD0rg","type":"artist","name":"Saschienne"}],"album":{"id":"4RhYcvUh2VpTi5ojBQmk2t","name":"Unknown"},"preview_url":null,"track_number":7,"href":"https://api.spotify.com/v1/tracks/0xirw16sHgeRNcYirbHCK5"}},{"added_at":"2016-01-14T16:19:04Z","added_by":{"id":"1128723762","display_name":null},"track":{"id":"6e2CGKya5ALCNVVH1Kv7iU","uri":"spotify:track:6e2CGKya5ALCNVVH1Kv7iU","name":"Hate Street Dialogue","artists":[{"id":"5PrHzxc3kFm4hIrGNmelpX","type":"artist","name":"Rodríguez"}],"album":{"id":"2knVXO0fQuDVrk5GmLp3oU","name":"Cold Fact"},"preview_url":null,"track_number":5,"href":"https://api.spotify.com/v1/tracks/6e2CGKya5ALCNVVH1Kv7iU"}},{"added_at":"2016-01-14T16:19:04Z","added_by":{"id":"1128723762","display_name":null},"track":{"id":"0FIJscQHEkL1c1tPhJUwoW","uri":"spotify:track:0FIJscQHEkL1c1tPhJUwoW","name":"Smile For You","artists":[{"id":"2dUsAHSrnsFvNpNpAV4aGI","type":"artist","name":"Mees Dierdorp"}],"album":{"id":"0vMN10KZr6FZqZ4IESqCNw","name":"Wild Window"},"preview_url":"https://p.scdn.co/mp3-preview/fa85fd4bba993029bb87e397645f3ca62e4ce289?cid=774b29d4f13844c495f206cafdad9c86","track_number":8,"href":"https://api.spotify.com/v1/tracks/0FIJscQHEkL1c1tPhJUwoW"}},{"added_at":"2016-01-14T16:19:04Z","added_by":{"id":"1128723762","display_name":null},"track":{"id":"29npoIBIrvLL0jTEfhS2fI","uri":"spotify:track:29npoIBIrvLL0jTEfhS2fI","name":"Up Past The Nursery - Ivan Smagghe Edit","artists":[{"id":"3UkN1XeK2D4wD4uhtJx4vb","type":"artist","name":"Suuns"}],"album":{"id":"5j16I7AHPOGsZaXStz5fcX","name":"Images Du Futur Remixes"},"preview_url":null,"track_number":5,"href":"https://api.spotify.com/v1/tracks/29npoIBIrvLL0jTEfhS2fI"}},{"added_at":"2016-01-14T16:19:04Z","added_by":{"id":"1128723762","display_name":null},"track":{"id":"3vzigG3TOPyKjzqWRKatKF","uri":"spotify:track:3vzigG3TOPyKjzqWRKatKF","name":"Reverse - Anger","artists":[{"id":"0qG2Tf6fJaCuWKGz1IitKa","type":"artist","name":"Moriarty"}],"album":{"id":"6Dx95qiRnig7JG4UoZtyFA","name":"Epitaph"},"preview_url":"https://p.scdn.co/mp3-preview/399efaf8a111a28223077ffa051a8f92c25490f4?cid=774b29d4f13844c495f206cafdad9c86","track_number":2,"href":"https://api.spotify.com/v1/tracks/3vzigG3TOPyKjzqWRKatKF"}},{"added_at":"2016-01-14T16:19:04Z","added_by":{"id":"1128723762","display_name":null},"track":{"id":"3PzVdQUe51QlmzZNwPJrXE","uri":"spotify:track:3PzVdQUe51QlmzZNwPJrXE","name":"Down the West Side","artists":[{"id":"0MiDH0wKRXC4IjCCPAwbE9","type":"artist","name":"M+A"}],"album":{"id":"10amdXA7JR4KOIpq0cwxMY","name":"These Days"},"preview_url":"https://p.scdn.co/mp3-preview/0a7ecf61711ba9746d8f08f65c3a496811f8049c?cid=774b29d4f13844c495f206cafdad9c86","track_number":3,"href":"https://api.spotify.com/v1/tracks/3PzVdQUe51QlmzZNwPJrXE"}},{"added_at":"2016-01-14T16:19:04Z","added_by":{"id":"1128723762","display_name":null},"track":{"id":"6EX5fV0fvFLZ3bK5Q4RS4i","uri":"spotify:track:6EX5fV0fvFLZ3bK5Q4RS4i","name":"Hey Now - Zero 7 Remix","artists":[{"id":"3Bd1cgCjtCI32PYvDC3ynO","type":"artist","name":"London Grammar"},{"id":"0K6dzg3fVKwHIKobYJM25I","type":"artist","name":"Zero 7"}],"album":{"id":"5IznFue91ycZ4X146LjxMc","name":"If You Wait - Remixes 2"},"preview_url":null,"track_number":3,"href":"https://api.spotify.com/v1/tracks/6EX5fV0fvFLZ3bK5Q4RS4i"}},{"added_at":"2016-01-14T16:19:04Z","added_by":{"id":"1128723762","display_name":null},"track":{"id":"11RSAj9BMemLu7Pwfyz5yT","uri":"spotify:track:11RSAj9BMemLu7Pwfyz5yT","name":"Reykjavik","artists":[{"id":"6eNOjuJSfKkAvbiGW90AkZ","type":"artist","name":"Joachim Pastor"}],"album":{"id":"5eJEBrrCfrvUA772RHQPRr","name":"Reykjavik"},"preview_url":null,"track_number":1,"href":"https://api.spotify.com/v1/tracks/11RSAj9BMemLu7Pwfyz5yT"}},{"added_at":"2016-01-14T16:19:04Z","added_by":{"id":"1128723762","display_name":null},"track":{"id":"0y6Mp5Y1OxHtzxi6AwewPt","uri":"spotify:track:0y6Mp5Y1OxHtzxi6AwewPt","name":"Catamaran","artists":[{"id":"2yDodJUwXfdHzg4crwslUp","type":"artist","name":"Allah-Las"}],"album":{"id":"3XgVl7O0ddImgVBtlEPdDw","name":"Allah-Las"},"preview_url":null,"track_number":1,"href":"https://api.spotify.com/v1/tracks/0y6Mp5Y1OxHtzxi6AwewPt"}},{"added_at":"2016-01-14T16:19:04Z","added_by":{"id":"1128723762","display_name":null},"track":{"id":"0eKyoAUzlZsmgw2jdEkeEx","uri":"spotify:track:0eKyoAUzlZsmgw2jdEkeEx","name":"All Away","artists":[{"id":"2zlZMYbK8cb2rChIplhveR","type":"artist","name":"Art of Shades"},{"id":"32tARZBvNtyWp0QZkJmhbh","type":"artist","name":"Soukaïna"}],"album":{"id":"3UqW6ZeabbDSA6EBQSYQuO","name":"Into the Waves"},"preview_url":null,"track_number":2,"href":"https://api.spotify.com/v1/tracks/0eKyoAUzlZsmgw2jdEkeEx"}},{"added_at":"2016-01-14T16:19:04Z","added_by":{"id":"1128723762","display_name":null},"track":{"id":"2aH8tLE6nIgQLLGsUv3KjO","uri":"spotify:track:2aH8tLE6nIgQLLGsUv3KjO","name":"Ghost (feat. Clap Your Hands Say Yeah)","artists":[{"id":"4mncDFjVLUa3s025Tct3Ry","type":"artist","name":"Claptone"},{"id":"1jSaZgaKHmgc7VTgML528r","type":"artist","name":"Clap Your Hands Say Yeah"}],"album":{"id":"6Gvo0fRYJ03X10GYO7Jgpt","name":"Ghost"},"preview_url":null,"track_number":1,"href":"https://api.spotify.com/v1/tracks/2aH8tLE6nIgQLLGsUv3KjO"}},{"added_at":"2016-01-14T16:19:04Z","added_by":{"id":"1128723762","display_name":null},"track":{"id":"6DpFDr9jWUan60x5Vk5HdX","uri":"spotify:track:6DpFDr9jWUan60x5Vk5HdX","name":"Small Things","artists":[{"id":"5schNIzWdI9gJ1QRK8SBnc","type":"artist","name":"Ben Howard"}],"album":{"id":"4EcVVeYCeafIQk383MQfp5","name":"I Forget Where We Were"},"preview_url":null,"track_number":1,"href":"https://api.spotify.com/v1/tracks/6DpFDr9jWUan60x5Vk5HdX"}},{"added_at":"2016-01-14T16:19:04Z","added_by":{"id":"1128723762","display_name":null},"track":{"id":"0Ag5IkPo62zt6tlhRbsSaS","uri":"spotify:track:0Ag5IkPo62zt6tlhRbsSaS","name":"Sun Down","artists":[{"id":"6hhA8TKRNryM8FNzqCqdDO","type":"artist","name":"Tricky"},{"id":"7hjxsoV8sMKKyjLLcOacAF","type":"artist","name":"Tirzah"}],"album":{"id":"5BZaqwXCHm6F3mAlbm2rmI","name":"Adrian Thaws"},"preview_url":null,"track_number":1,"href":"https://api.spotify.com/v1/tracks/0Ag5IkPo62zt6tlhRbsSaS"}},{"added_at":"2016-01-14T16:19:04Z","added_by":{"id":"1128723762","display_name":null},"track":{"id":"2pbZ8wGS6vsdZmxSgawnzn","uri":"spotify:track:2pbZ8wGS6vsdZmxSgawnzn","name":"Glare","artists":[{"id":"49BJFNmL0Qb0eUEROwcTlO","type":"artist","name":"Sheep, Dog & Wolf"}],"album":{"id":"3jAghMkYpjLYbl3NyvCqw8","name":"Egospect"},"preview_url":null,"track_number":2,"href":"https://api.spotify.com/v1/tracks/2pbZ8wGS6vsdZmxSgawnzn"}},{"added_at":"2016-01-14T16:19:04Z","added_by":{"id":"1128723762","display_name":null},"track":{"id":"76JDDH4UrSfQhqSw3SK1A2","uri":"spotify:track:76JDDH4UrSfQhqSw3SK1A2","name":"Believe (feat. Chelou)","artists":[{"id":"1BiGjy3Kg99ZgL7E2Qb4Td","type":"artist","name":"Nocturnal Sunshine"},{"id":"2RwfRD2vlkdztGtVXENShq","type":"artist","name":"Chelou"}],"album":{"id":"2gKMzNbXy6UHyCweNT42GZ","name":"Nocturnal Sunshine"},"preview_url":null,"track_number":2,"href":"https://api.spotify.com/v1/tracks/76JDDH4UrSfQhqSw3SK1A2"}},{"added_at":"2016-01-14T16:19:04Z","added_by":{"id":"1128723762","display_name":null},"track":{"id":"5zWTzwXAI6jpW9FQAz6kf3","uri":"spotify:track:5zWTzwXAI6jpW9FQAz6kf3","name":"How Many Times","artists":[{"id":"2vf4pRsEY6LpL5tKmqWb64","type":"artist","name":"Elderbrook"}],"album":{"id":"1Fxc2EGQoVgdAVlHGU3p9I","name":"Simmer Down"},"preview_url":null,"track_number":3,"href":"https://api.spotify.com/v1/tracks/5zWTzwXAI6jpW9FQAz6kf3"}},{"added_at":"2016-01-14T16:19:04Z","added_by":{"id":"1128723762","display_name":null},"track":{"id":"5wNHIIiOozym96IHY7Tw4v","uri":"spotify:track:5wNHIIiOozym96IHY7Tw4v","name":"Blame","artists":[{"id":"4bS7w1U8P3Zuaa5jmj3mvN","type":"artist","name":"Denai Moore"}],"album":{"id":"1bgt9l2VTUCeKtAFnerE3p","name":"Elsewhere"},"preview_url":null,"track_number":3,"href":"https://api.spotify.com/v1/tracks/5wNHIIiOozym96IHY7Tw4v"}},{"added_at":"2016-01-14T16:19:04Z","added_by":{"id":"1128723762","display_name":null},"track":{"id":"5xBFcWpd7SxKsXaFwafKSn","uri":"spotify:track:5xBFcWpd7SxKsXaFwafKSn","name":"Wilkie","artists":[{"id":"2GvwZbDjH1DbQpodGKENDw","type":"artist","name":"Roman Flügel"}],"album":{"id":"1o749fQxB6OKWsieznl9R9","name":"Happiness Is Happening"},"preview_url":null,"track_number":5,"href":"https://api.spotify.com/v1/tracks/5xBFcWpd7SxKsXaFwafKSn"}},{"added_at":"2016-01-14T16:19:04Z","added_by":{"id":"1128723762","display_name":null},"track":{"id":"5yvX1qvfhN36ZZDZ3E2z8T","uri":"spotify:track:5yvX1qvfhN36ZZDZ3E2z8T","name":"Go Back","artists":[{"id":"6JpZEemWmunccsrHXFUOgi","type":"artist","name":"Tony Allen"},{"id":"0O98jlCaPzvsoei6U5jfEL","type":"artist","name":"Damon Albarn"}],"album":{"id":"5OiUURWMLnRycOmHPUm5Wy","name":"Film of Life"},"preview_url":null,"track_number":7,"href":"https://api.spotify.com/v1/tracks/5yvX1qvfhN36ZZDZ3E2z8T"}},{"added_at":"2016-01-14T16:19:04Z","added_by":{"id":"1128723762","display_name":null},"track":{"id":"4jKSl2zp59HzK76UcuFtJs","uri":"spotify:track:4jKSl2zp59HzK76UcuFtJs","name":"Rich","artists":[{"id":"6hV6oxGLeLFw17DGjIPkYD","type":"artist","name":"Cosmo Sheldrake"}],"album":{"id":"3d9iZC1iQYBTtv7cSCWdJW","name":"Pelicans We"},"preview_url":"https://p.scdn.co/mp3-preview/efe0ddbaa804dd4795be6b739ffe4514c0091f68?cid=774b29d4f13844c495f206cafdad9c86","track_number":4,"href":"https://api.spotify.com/v1/tracks/4jKSl2zp59HzK76UcuFtJs"}},{"added_at":"2016-01-14T16:19:04Z","added_by":{"id":"1128723762","display_name":null},"track":{"id":"4easPP2Np7z0PNCbR6psCv","uri":"spotify:track:4easPP2Np7z0PNCbR6psCv","name":"Tactics - Tom Tukker Remix","artists":[{"id":"7HPVAGjCVDzP7xcNrkwgxL","type":"artist","name":"CUT_"}],"album":{"id":"1rueuOtob9T4XfjoZqhTpY","name":"Chapter I - Remixed"},"preview_url":null,"track_number":1,"href":"https://api.spotify.com/v1/tracks/4easPP2Np7z0PNCbR6psCv"}},{"added_at":"2016-01-14T16:19:04Z","added_by":{"id":"1128723762","display_name":null},"track":{"id":"5NbasL13ZyTu02X1R5XILi","uri":"spotify:track:5NbasL13ZyTu02X1R5XILi","name":"Ordinary Man","artists":[{"id":"6vgw0jwJkUnW2NR1rzsQU3","type":"artist","name":"Chinese Man"}],"album":{"id":"5sG4aODV6qWPX0J7omBcnC","name":"The Groove Sessions, Vol. 2"},"preview_url":"https://p.scdn.co/mp3-preview/364d05159eae757dea7116baf5034ed2b56f2663?cid=774b29d4f13844c495f206cafdad9c86","track_number":7,"href":"https://api.spotify.com/v1/tracks/5NbasL13ZyTu02X1R5XILi"}},{"added_at":"2016-01-14T16:19:04Z","added_by":{"id":"1128723762","display_name":null},"track":{"id":"18d4Pv6swQM9C9Kr4qWw5h","uri":"spotify:track:18d4Pv6swQM9C9Kr4qWw5h","name":"Deeper Shadows","artists":[{"id":"20o7mwLphfnviZKGPw1gi3","type":"artist","name":"Jaakko Eino Kalevi"}],"album":{"id":"2EXncBXmOeBCmcEELBS4Cu","name":"Jaakko Eino Kalevi"},"preview_url":null,"track_number":3,"href":"https://api.spotify.com/v1/tracks/18d4Pv6swQM9C9Kr4qWw5h"}},{"added_at":"2016-01-14T16:19:04Z","added_by":{"id":"1128723762","display_name":null},"track":{"id":"0WKu88lzoWGL9ccgh13l5X","uri":"spotify:track:0WKu88lzoWGL9ccgh13l5X","name":"Chess","artists":[{"id":"4dGwtd1FYag1VY1vaR1U8y","type":"artist","name":"Petite Noir"}],"album":{"id":"3GpVIyrRRWHGQb4QfVz4Ds","name":"Chess"},"preview_url":null,"track_number":1,"href":"https://api.spotify.com/v1/tracks/0WKu88lzoWGL9ccgh13l5X"}},{"added_at":"2016-01-14T16:19:04Z","added_by":{"id":"1128723762","display_name":null},"track":{"id":"5GeIdhQ2HZ86I9HsQwvRAP","uri":"spotify:track:5GeIdhQ2HZ86I9HsQwvRAP","name":"Kingdom Leader","artists":[{"id":"1SFz3S9eSUTc49ysstadiO","type":"artist","name":"Boo Seeka"}],"album":{"id":"03EMOcMFTB5rep0KfqI9XX","name":"Kingdom Leader – Single"},"preview_url":"https://p.scdn.co/mp3-preview/3a3657eeba10e455c34c398218e57bd5bdb2a607?cid=774b29d4f13844c495f206cafdad9c86","track_number":1,"href":"https://api.spotify.com/v1/tracks/5GeIdhQ2HZ86I9HsQwvRAP"}},{"added_at":"2016-01-14T16:19:04Z","added_by":{"id":"1128723762","display_name":null},"track":{"id":"6FrWcLu0aYg14wV4mnYMlH","uri":"spotify:track:6FrWcLu0aYg14wV4mnYMlH","name":"You Don't Know Me","artists":[{"id":"3kZdsaTYgaaolNxpnJ4iDe","type":"artist","name":"Son Lux"}],"album":{"id":"3RAdsUGbFZq3WPcdep3kid","name":"Bones"},"preview_url":null,"track_number":4,"href":"https://api.spotify.com/v1/tracks/6FrWcLu0aYg14wV4mnYMlH"}},{"added_at":"2016-01-14T16:19:04Z","added_by":{"id":"1128723762","display_name":null},"track":{"id":"0h8ojQz5giqSp3Q5EWUrRv","uri":"spotify:track:0h8ojQz5giqSp3Q5EWUrRv","name":"Gold (Flume Re-Work)","artists":[{"id":"2Q0MyH5YMI5HPQjFjlq5g3","type":"artist","name":"Nick Murphy / Chet Faker"}],"album":{"id":"6sqQFchi2DHwhAFfm5x5ud","name":"Gold (Flume Re-Work)"},"preview_url":null,"track_number":1,"href":"https://api.spotify.com/v1/tracks/0h8ojQz5giqSp3Q5EWUrRv"}},{"added_at":"2016-01-14T16:19:04Z","added_by":{"id":"1128723762","display_name":null},"track":{"id":"3voTMesxrpLZ3MQRYHKAc1","uri":"spotify:track:3voTMesxrpLZ3MQRYHKAc1","name":"Death Is A Girl","artists":[{"id":"07xbJ7SM1JopFtI1qXvSww","type":"artist","name":"Mini Mansions"}],"album":{"id":"2gb89wVcYeN7P31s93hEQy","name":"The Great Pretenders"},"preview_url":null,"track_number":2,"href":"https://api.spotify.com/v1/tracks/3voTMesxrpLZ3MQRYHKAc1"}}]}
